video_highlight_generator/__init__.py
video_highlight_generator/main.py
video_highlight_generator/core/__init__.py
video_highlight_generator/core/audio_manager.py
video_highlight_generator/core/database.py
video_highlight_generator/core/face_detector.py
video_highlight_generator/core/image_processor.py
video_highlight_generator/core/video_generator.py
video_highlight_generator/static/index.html
video_highlight_generator/static/assets/index-BImKRfSc.css
video_highlight_generator/static/assets/index-CZmmrITC.js
video_highlight_generator-0.1.2.dist-info/licenses/LICENSE
video_highlight_generator-0.1.2.dist-info/METADATA
video_highlight_generator-0.1.2.dist-info/WHEEL
video_highlight_generator-0.1.2.dist-info/entry_points.txt
video_highlight_generator-0.1.2.dist-info/top_level.txt
video_highlight_generator-0.1.2.dist-info/RECORD
