Metadata-Version: 2.4
Name: video_highlight_generator
Version: 0.1.2
Summary: A powerful, standalone AI tool that automatically creates engaging highlight videos from your photo collections.
Author: Wael SAHLI
Project-URL: Homepage, https://github.com/overcrash66/Video_Highlight_Generator_from_images
Project-URL: Repository, https://github.com/overcrash66/Video_Highlight_Generator_from_images
Requires-Python: >=3.10
License-File: LICENSE
Requires-Dist: fastapi
Requires-Dist: uvicorn
Requires-Dist: opencv-python
Requires-Dist: torch
Requires-Dist: facenet-pytorch
Requires-Dist: moviepy>=2.0.0.dev0
Requires-Dist: numpy>=2.0.0
Requires-Dist: Pillow
Requires-Dist: python-multipart
Requires-Dist: aiofiles
Dynamic: license-file
